LICENSE
MANIFEST.in
README.rst
check_api.py
setup.cfg
setup.py
haiker/__init__.py
haiker/api.py
haiker/auth.py
haiker/error.py
haiker/types.py
haiker/utils.py
hatena_haiker.egg-info/PKG-INFO
hatena_haiker.egg-info/SOURCES.txt
hatena_haiker.egg-info/dependency_links.txt
hatena_haiker.egg-info/requires.txt
hatena_haiker.egg-info/top_level.txt
tests/__init__.py
tests/samples.py
tests/test_api.py
tests/test_auth.py
tests/test_error.py
tests/test_types.py
tests/test_utils.py