Metadata-Version: 1.1
Name: hatena-haiker
Version: 0.4.0
Summary: Hatena Haiku for Python 3
Home-page: https://github.com/saltcandy123/hatena-haiker/
Author: @saltcandy123
Author-email: saltcandy123+haiker@gmail.com
License: MIT License
Keywords: hatena haiku api
Platform: UNKNOWN
Classifier: Development Status :: 3 - Alpha
Classifier: Intended Audience :: Developers
Classifier: License :: OSI Approved :: MIT License
Classifier: Operating System :: OS Independent
Classifier: Programming Language :: Python
Classifier: Programming Language :: Python :: 3
Classifier: Programming Language :: Python :: 3.2
Classifier: Programming Language :: Python :: 3.3
Classifier: Programming Language :: Python :: 3.4
Classifier: Programming Language :: Python :: 3.5
Classifier: Programming Language :: Python :: 3 :: Only
Classifier: Topic :: Software Development :: Libraries
